x123pan/__init__.py
x123pan/src/__init__.py
x123pan/src/api.py
x123pan/src/const.py
x123pan/src/tool.py
x123pan/src/type.py
x123pan/util/__init__.py
x123pan/util/all.py
x123pan-0.3.0.dist-info/licenses/LICENSE
x123pan-0.3.0.dist-info/METADATA
x123pan-0.3.0.dist-info/WHEEL
x123pan-0.3.0.dist-info/top_level.txt
x123pan-0.3.0.dist-info/RECORD
