Metadata-Version: 2.4
Name: x123pan
Version: 0.3.0
Summary: 123云盘官方Open API Python封装库
Home-page: https://github.com/xxxxxfpx/123PanOpen
Author: xxxxxfpx
Author-email: xxxxfpx <1564430143@qq.com>
Maintainer-email: xxxxfpx <1564430143@qq.com>
License: MIT
Project-URL: Homepage, https://github.com/xxxxxfpx/123PanOpen
Project-URL: Documentation, https://github.com/xxxxxfpx/123PanOpen#readme
Project-URL: Repository, https://github.com/xxxxxfpx/123PanOpen
Project-URL: Issues, https://github.com/xxxxxfpx/123PanOpen/issues
Keywords: 123pan,cloud,api,storage,file-manager
Classifier: Development Status :: 4 - Beta
Classifier: Intended Audience :: Developers
Classifier: License :: OSI Approved :: MIT License
Classifier: Programming Language :: Python
Classifier: Programming Language :: Python :: 3
Classifier: Programming Language :: Python :: 3.8
Classifier: Programming Language :: Python :: 3.9
Classifier: Programming Language :: Python :: 3.10
Classifier: Programming Language :: Python :: 3.11
Classifier: Programming Language :: Python :: 3.12
Classifier: Programming Language :: Python :: Implementation :: CPython
Classifier: Programming Language :: Python :: Implementation :: PyPy
Classifier: Topic :: Software Development :: Libraries :: Python Modules
Classifier: Topic :: Internet :: WWW/HTTP :: Dynamic Content
Requires-Python: >=3.8.0
License-File: LICENSE
Requires-Dist: requests>=2.25.0
Requires-Dist: pydantic>=1.8.0
Provides-Extra: dev
Requires-Dist: pytest>=7.0.0; extra == "dev"
Requires-Dist: pytest-cov>=4.0.0; extra == "dev"
Requires-Dist: pytest-mock>=3.10.0; extra == "dev"
Requires-Dist: ruff>=0.1.0; extra == "dev"
Requires-Dist: black>=23.0.0; extra == "dev"
Requires-Dist: mypy>=1.7.0; extra == "dev"
Requires-Dist: pre-commit>=3.0.0; extra == "dev"
Dynamic: author
Dynamic: home-page
Dynamic: license-file
Dynamic: requires-python
